mig_pur_py/__init__.py
mig_pur_py-0.1.0.dist-info/WHEEL
mig_pur_py-0.1.0.dist-info/METADATA
mig_pur_py-0.1.0.dist-info/RECORD
